src/data_memory.v
module data_memory(
    input wire clk,
    input wire rst,

    input wire mem_read,
    input wire mem_write,
    input wire [7:0] address,
    input wire [7:0] write_data,
    output reg [7:0] read_data
);
     // RAM
    reg [7:0] ram [0:255];

    integer i;
    initial begin
        for (i = 0; i < 256; i = i + 1) begin
            ram[i] = 8'b0;
        end
    end

    // WRITE logic
    always @(posedge clk or posedge rst) begin
        if (rst) begin
            // Initialize RAM to zero on reset
            for (i = 0; i < 256; i = i + 1) begin
                ram[i] <= 8'b0;
            end
            read_data <= 8'b0;
        end else if (mem_write) begin
            ram[address] <= write_data[7:0];
        end
    
    end

    // READ logic
    always @(*) begin
        if (mem_read) begin
            read_data = ram[address];
        end
        else begin
            read_data = 8'b0;
        end
    end

endmodule

src/alu.v
/*
    0000	PASS THRU
    0001	AND
    0010	OR
    0011	NOT
    0100	XOR
    0101	LSL
    0110	LSR
    0111	ASR
    1000	ADD
    1001	SUB
    1010	MUL
    1011	NEG
    1100	ADDI
    1101	MULI
    1110	ADC
    1111	CMP

*/
module alu(
    input wire [7:0] a,
    input wire [7:0] b,
    input wire [3:0] op,
    input wire carry_in,
    input wire overflow_in,
    output reg [7:0] result,
    output reg zero,
    output reg carry,
    output reg sign,
    output reg overflow
);
    reg [8:0] sum; // extended for carry
    reg [7:0] b_comp;
    reg [15:0] mul_result; // for multiplication

    always @(*) begin

        sum = 9'b0;

        case (op)
            4'b0000: result = a; // PASS THRU
            4'b0001: result = a & b; // AND
            4'b0010: result = a | b; // OR
            4'b0011: result = ~a; // NOT
            4'b0100: result = a ^ b; // XOR
            4'b0101:result = a << b; // LSL
            4'b0110:result = a >> b; // LSR
            4'b0111: result = $signed(a) >>> b; // ASR
            4'b1000,4'b1100: begin // ADD
                sum = a + b;
                result = sum[7:0];
            end
            4'b1001: begin // SUB
                b_comp = ~b + 1; // Two's complement of b
                sum = a + b_comp;
                result = sum[7:0];
            end
            4'b1010,4'b1101: begin
                mul_result = a * b; // MUL
                result = mul_result[7:0];
            end
            4'b1011: result = -a; // NEG
            4'b1110: begin // ADC (Add with Carry)
                sum = a + b + carry_in;
                result = sum[7:0];
            end
            4'b1111: begin // CMP (compare)
                b_comp = ~b + 1; // Two's complement of b
                sum = a + b_comp;
                carry = sum[8];
                overflow = (a[7] != b_comp[7]) && (sum[7] != a[7]);
                zero = (sum[7:0] == 0);
                sign = sum[7];
                result = 8'b0; // CMP does not produce a result
            end
            default: result = 8'b0;
        endcase
    end
endmodule

src/reg_file.v
//8 registers (R0-R7) of 16 bits each
//R0 is always 0
//R7 is reserved for JAL and RET but can be used
module reg_file(
    input wire clk,
    input wire rst,

    input wire we,
    input wire [2:0] wa,
    input wire [7:0] wd,

    input wire [2:0] ra1,
    output wire [7:0] rd1,

    input wire [2:0] ra2,
    output wire [7:0] rd2
);
    // 8 registers of 8 bits each
    reg [7:0] registers [0:7];

    // Write operation
    always @(posedge clk or posedge rst) begin
        if (rst) begin
            integer i;
            for (i = 0; i < 8; i = i + 1) begin
                registers[i] <= 8'b0;
            end
        end else if (we && (wa != 3'b0)) begin // Prevent writing to register 0 (which is always 0)
            registers[wa] <= wd;
        end
    end

    // Read operations
    assign rd1 = (ra1 == 3'd0) ? 8'h00 : registers[ra1];
    assign rd2 = (ra2 == 3'd0) ? 8'h00 : registers[ra2];
endmodule

src/instruction_decoder.v
module instruction_decoder(
    input wire [15:0] instruction,

    output reg [3:0] alu_opcode,
    output wire [2:0] rs,
    output wire [2:0] rt,
    output reg [2:0] rd,
    output wire [4:0] imm5,
    output reg pass_carry,
    output reg isImm,

    output reg mem_read,
    output reg mem_write,
    output reg [7:0] mem_addr8,
    output reg addr_is_reg, // if 1 then mem_addr8 is actually a register number whose value is the address to access

    output reg reg_write,

    output reg halt,

    output reg jump,
    output reg branch,
    output wire [10:0] jump_addr11,

    output reg [1:0] wb_sel // register write back 00=ALU result, 01=Memory data, 10=Immediate (for LOADI) 11=PC+1 (for JAL)
);
    wire [4:0] opcode;
    wire [2:0] rd_wire;

    assign opcode = instruction[15:11];
    assign rs = instruction[10:8];
    
    assign rd_wire = instruction[2:0];
    assign rt = (opcode == 5'b00010 || opcode == 5'b01111) ? rd_wire : instruction[7:5]; // for store instructions the value to store is in rd field, but the instruction decoder changes the rt addr to what ever the rd said in the opcode
    assign imm5 = instruction[4:0];
    assign jump_addr11 = instruction[10:0];
    assign mem_addr8 = instruction[10:3];

    always @(*) begin
        alu_opcode  = 4'b0000;
        isImm       = 1'b0;
        pass_carry  = 1'b0;
        
        mem_read    = 1'b0;
        mem_write   = 1'b0;
        addr_is_reg = 1'b0;

        rd          = rd_wire; // default destination register is rd field
        reg_write   = 1'b0;
        
        halt        = 1'b0;
        branch      = 1'b0;
        jump        = 1'b0;
        
        wb_sel      = 2'b00; // default is ALU
        //if opcode starts with 1 then its an alu operation
        //most alu operations write to reg so default it too
        if (opcode[4]) begin
            alu_opcode = opcode[3:0];
            reg_write = 1'b1;
        end

        case (opcode)
            5'b00000: begin //HALT
                halt = 1;
            end
            5'b00001: begin //LOAD
                mem_read = 1;
                wb_sel = 2'b01; // write back memory data
                reg_write = 1;
            end
            5'b00010: begin //STORE
                mem_write = 1;
            end
            5'b00011: begin //LOADI
                wb_sel = 2'b10; // write back immediate
                reg_write = 1;
                isImm = 1;
            end
            5'b00100: begin //BEQ
                branch = 1;
            end
            5'b00101: begin //BNE
                branch = 1;
            end
            5'b00110: begin //BLT
                branch = 1;
            end
            5'b00111: begin //BGT
                branch = 1;
            end
            5'b01000: begin //BLE
                branch = 1;
            end
            5'b01001: begin //BGE
                branch = 1;
            end
            5'b01010: begin //JUMP
                jump = 1;
            end
            5'b01011: begin //JAL
                jump = 1;
                reg_write = 1;
                rd = 3'b111; // write back to R7
                wb_sel = 2'b11; // write back PC+1
            end
            5'b01100: begin //RET
                jump = 1;
            end
            5'b01101: begin //MOVE
                alu_opcode = 4'b0000; // PASS THRU
                reg_write = 1;
            end
            5'b01110: begin //LOADR
                mem_read = 1;
                wb_sel = 2'b01; // write back memory data
                reg_write = 1;
                addr_is_reg = 1;
            end
            5'b01111: begin  //STORER
                mem_write = 1;
                addr_is_reg = 1;
            end
            5'b10000: begin //NOP
                reg_write = 0;
            end
            /*
            from 10001 to 11011 (which are the following)
            AND
            OR
            NOT
            XOR
            LSL
            LSR
            ASR
            ADD
            SUB
            NEG
            have already been handled by the alu if check above
            */
            5'b11100: begin //ADDI
                isImm = 1;
            end
            5'b11101: begin //MULI
                isImm = 1;
            end
            5'b11110: begin //ADC
                pass_carry = 1;
            end
            5'b11111: begin //CMP
                reg_write = 0;
            end
        endcase
    end
endmodule

src/instruction_memory.v
module instruction_memory(
    input wire [10:0] address,
    output reg [15:0] instruction
);
    // Simple instruction memory with 2048 instructions
    reg [15:0] memory [0:2047]; // Initialize all instructions to 0
    integer i;
    initial begin
        for (i = 0; i < 2048; i = i + 1) begin
            memory[i] = 16'h0000;
        end
        //$readmemb("programs/simple_add.bin", memory);
        $readmemb("programs/fibbonaci.bin", memory);
    end

    always @(*) begin
        instruction = memory[address[10:0]]; // Use lower 11 bits for addressing
    end
endmodule

src/fat_cat_cpu.v
module fat_cat_cpu(
    input wire clk,
    input wire rst
);
    //Program counter
    reg [10:0] pc;
    reg [10:0] pc_next;
    always @(posedge clk or posedge rst) begin
        if (rst) begin
            pc <= 11'b0;
        end else begin
            pc <= pc_next;
        end
    end

    //Instruction memory
    wire [15:0] instruction;
    instruction_memory imem (
        .address(pc),
        .instruction(instruction)
    );
    //Instruction decoder
    wire [3:0] alu_opcode;
    wire [2:0] rs, rt;
    wire [2:0] rd;
    wire [4:0] imm5;
    wire pass_carry;
    wire isImm;
    wire mem_read, mem_write;
    wire [7:0] mem_addr8;
    wire addr_is_reg;
    wire reg_write;
    wire halt;
    wire jump, branch;
    wire [10:0] jump_addr11;
    wire [1:0] wb_sel;
    instruction_decoder idec (
        .instruction(instruction),
        .alu_opcode(alu_opcode),
        .rs(rs),
        .rt(rt),
        .rd(rd),
        .imm5(imm5),
        .pass_carry(pass_carry),
        .isImm(isImm),
        .mem_read(mem_read),
        .mem_write(mem_write),
        .mem_addr8(mem_addr8),
        .addr_is_reg(addr_is_reg),
        .reg_write(reg_write),
        .halt(halt),
        .jump(jump),
        .branch(branch),
        .jump_addr11(jump_addr11),
        .wb_sel(wb_sel)
    );

    //Register file
    wire [7:0] rs_data, rt_data;
    reg[7:0] wb_data;
    reg_file rfile(
        .clk(clk),
        .rst(rst),
        .we(reg_write),
        .ra1(rs),
        .ra2(rt),
        .wa(rd),
        .wd(wb_data),
        .rd1(rs_data),
        .rd2(rt_data)
    );
    //ALU
    wire [7:0] alu_result;
    reg carry_out, zero, sign, overflow;
    alu alu_unit (
        .op(alu_opcode),
        .a(rs_data),
        .b(isImm ? {3'b0, imm5} : rt_data),
        .carry_in(pass_carry ? carry_out : 1'b0),
        .result(alu_result),
        .carry(carry_out),
        .zero(zero),
        .sign(sign),
        .overflow(overflow)
    );
    //Write back MUX
    always @(*) begin
        case (wb_sel)
            2'b00: wb_data = alu_result; // ALU result
            2'b01: wb_data = mem_read_data;   // Memory data
            2'b10: wb_data = mem_addr8; // Immediate value
            2'b11: wb_data = pc + 11'b1; // PC + 1
            default: wb_data = 8'b0;
        endcase
    end
    //Data memory
    wire [7:0] mem_read_data;
    data_memory dmem (
        .clk(clk),
        .rst(rst),
        .mem_write(mem_write),
        .mem_read(mem_read),
        .address(addr_is_reg ? rs_data : mem_addr8),
        .write_data(rt_data), // store value is always in rt even though it says rd in the instruction set, but the instruction decoder changes the rt addr to what ever the rd said in the opcode
        .read_data(mem_read_data)
    );
    reg branch_taken;
    always @(*) begin
        branch_taken = 1'b0;
        if (branch) begin
            case (instruction[15:11]) // branch type
                5'b00100: branch_taken = zero;          // BEQ
                5'b00101: branch_taken = ~zero;         // BNE
                5'b00110: branch_taken = sign ^ overflow;          // BLT
                5'b00111: branch_taken = ~zero & ~(sign ^ overflow);         // BGT
                5'b01000: branch_taken = zero | (sign ^ overflow);      // BLE
                5'b01001: branch_taken = ~(sign ^ overflow);     // BGE
                default: branch_taken = 1'b0;
            endcase
        end
    end
    //Next PC logic
    assign pc_next = halt ? pc : 
                     jump ? jump_addr11 : 
                     branch_taken ? pc + jump_addr11 : 
                     pc + 11'b1;
endmodule

testbenches/fat_cat_cpu_testbench.v
module fat_cat_cpu_testbench;
    // Signals
    reg clk;
    reg rst;

    // Instantiate the CPU
    fat_cat_cpu uut (
        .clk(clk),
        .rst(rst)
    );

    // Clock generation
    always #5 clk = ~clk;

    integer i; // For loops

    initial begin
        $dumpfile("testbenches/fat_cat_cpu_testbench.vcd");
        $dumpvars(0, fat_cat_cpu_testbench);
        // Initialize signals
        clk = 0;
        rst = 1;

        $display("--- Starting CPU Simulation ---");
        #10 rst = 0;

        // Execution Loop
        while (!uut.halt) begin
            @(posedge clk);
             $display("Time: %t | PC: %h | Instr: %b | R1: %d | R2: %d | R3: %d | R4: %d | R5: %d | R6:%d | Zero=%d | Carry=%d | Overflow=%d | Sign=%d", $time, uut.pc, uut.instruction, uut.rfile.registers[1], uut.rfile.registers[2],uut.rfile.registers[3],uut.rfile.registers[4],uut.rfile.registers[5], uut.rfile.registers[6], uut.zero, uut.carry_out, uut.overflow, uut.sign);
        end

        // Execution has halted [cite: 67, 83]
        $display("\n--- Execution Halted at Time %t ---", $time);
        $display("Final PC: %h", uut.pc);

        // --- Print Register File ---
        $display("\n--- Register File (R0-R7) ---");
        $display("Reg | Value (Hex) | Value (Dec)");
        $display("----|-------------|------------");
        for (i = 0; i < 8; i = i + 1) begin
            // Accessing internal registers array from reg_file module 
            $display("R%0d  | %h          | %d", i, uut.rfile.registers[i], uut.rfile.registers[i]);
        end

        // --- Print First 16 Bytes of Data Memory ---
        $display("\n--- Data Memory (First 16 Bytes) ---");
        $display("Addr | Value (Hex) | Value (Dec)");
        $display("-----|-------------|------------");
        for (i = 0; i < 128; i = i + 1) begin
            // Accessing internal ram array from data_memory module 
            $display("0x%02h | %h          | %d", i, uut.dmem.ram[i], uut.dmem.ram[i]);
        end

        $display("\n--- Simulation Finished ---");
        $finish;
    end

endmodule

testbenches/fat_cat_cpu_testbench.vcd
$date
	Thu Feb 19 15:07:07 2026
$end
$version
	Icarus Verilog
$end
$timescale
	1s
$end
$scope module fat_cat_cpu_testbench $end
$var reg 1 ! clk $end
$var reg 1 " rst $end
$var integer 32 # i [31:0] $end
$scope module uut $end
$var wire 1 ! clk $end
$var wire 1 " rst $end
$var wire 1 $ zero $end
$var wire 2 % wb_sel [1:0] $end
$var wire 1 & sign $end
$var wire 8 ' rt_data [7:0] $end
$var wire 3 ( rt [2:0] $end
$var wire 8 ) rs_data [7:0] $end
$var wire 3 * rs [2:0] $end
$var wire 1 + reg_write $end
$var wire 3 , rd [2:0] $end
$var wire 11 - pc_next [10:0] $end
$var wire 1 . pass_carry $end
$var wire 1 / overflow $end
$var wire 1 0 mem_write $end
$var wire 8 1 mem_read_data [7:0] $end
$var wire 1 2 mem_read $end
$var wire 8 3 mem_addr8 [7:0] $end
$var wire 11 4 jump_addr11 [10:0] $end
$var wire 1 5 jump $end
$var wire 1 6 isImm $end
$var wire 16 7 instruction [15:0] $end
$var wire 5 8 imm5 [4:0] $end
$var wire 1 9 halt $end
$var wire 1 : carry_out $end
$var wire 1 ; branch $end
$var wire 8 < alu_result [7:0] $end
$var wire 4 = alu_opcode [3:0] $end
$var wire 1 > addr_is_reg $end
$var reg 1 ? branch_taken $end
$var reg 11 @ pc [10:0] $end
$var reg 8 A wb_data [7:0] $end
$scope module alu_unit $end
$var wire 8 B b [7:0] $end
$var wire 1 C carry_in $end
$var wire 1 D overflow_in $end
$var wire 4 E op [3:0] $end
$var wire 8 F a [7:0] $end
$var reg 8 G b_comp [7:0] $end
$var reg 1 : carry $end
$var reg 16 H mul_result [15:0] $end
$var reg 1 / overflow $end
$var reg 8 I result [7:0] $end
$var reg 1 & sign $end
$var reg 9 J sum [8:0] $end
$var reg 1 $ zero $end
$upscope $end
$scope module dmem $end
$var wire 8 K address [7:0] $end
$var wire 1 ! clk $end
$var wire 1 " rst $end
$var wire 8 L write_data [7:0] $end
$var wire 1 0 mem_write $end
$var wire 1 2 mem_read $end
$var reg 8 M read_data [7:0] $end
$var integer 32 N i [31:0] $end
$upscope $end
$scope module idec $end
$var wire 3 O rt [2:0] $end
$var wire 3 P rs [2:0] $end
$var wire 3 Q rd_wire [2:0] $end
$var wire 5 R opcode [4:0] $end
$var wire 8 S mem_addr8 [7:0] $end
$var wire 11 T jump_addr11 [10:0] $end
$var wire 16 U instruction [15:0] $end
$var wire 5 V imm5 [4:0] $end
$var reg 1 > addr_is_reg $end
$var reg 4 W alu_opcode [3:0] $end
$var reg 1 ; branch $end
$var reg 1 9 halt $end
$var reg 1 6 isImm $end
$var reg 1 5 jump $end
$var reg 1 2 mem_read $end
$var reg 1 0 mem_write $end
$var reg 1 . pass_carry $end
$var reg 3 X rd [2:0] $end
$var reg 1 + reg_write $end
$var reg 2 Y wb_sel [1:0] $end
$upscope $end
$scope module imem $end
$var wire 11 Z address [10:0] $end
$var reg 16 [ instruction [15:0] $end
$var integer 32 \ i [31:0] $end
$upscope $end
$scope module rfile $end
$var wire 1 ! clk $end
$var wire 3 ] ra1 [2:0] $end
$var wire 3 ^ ra2 [2:0] $end
$var wire 1 " rst $end
$var wire 3 _ wa [2:0] $end
$var wire 8 ` wd [7:0] $end
$var wire 1 + we $end
$var wire 8 a rd2 [7:0] $end
$var wire 8 b rd1 [7:0] $end
$scope begin $unm_blk_11 $end
$var integer 32 c i [31:0] $end
$upscope $end
$upscope $end
$upscope $end
$upscope $end
$enddefinitions $end
$comment Show the parameter values. $end
$dumpall
$end
#0
$dumpvars
b1000 c
b0 b
b0 a
b1100100 `
b110 _
b1 ^
b11 ]
b100000000000 \
b1101100100110 [
b0 Z
b10 Y
b110 X
b0 W
b100 V
b1101100100110 U
b1100100110 T
b1100100 S
b11 R
b110 Q
b11 P
b1 O
b100000000 N
b0 M
b0 L
b1100100 K
b0 J
b0 I
bx H
bx G
b0 F
b0 E
zD
0C
b100 B
b1100100 A
b0 @
0?
0>
b0 =
b0 <
0;
x:
09
b100 8
b1101100100110 7
16
05
b1100100110 4
b1100100 3
02
b0 1
00
x/
0.
b1 -
b110 ,
1+
b11 *
b0 )
b1 (
b0 '
x&
b10 %
x$
bx #
1"
0!
$end
#5
b1000 c
b100000000 N
1!
#10
0!
0"
#15
b10 -
b0 K
b0 A
b0 `
b0 B
b0 (
b0 O
b0 ^
b10 %
b10 Y
1+
b1 ,
b1 X
b1 _
16
b0 3
b0 S
b1 4
b1 T
b0 8
b0 V
b1 Q
b0 *
b0 P
b0 ]
b1100000000001 7
b1100000000001 U
b1100000000001 [
b1 @
b1 Z
1!
#20
0!
#25
b11 -
b1 K
b1 A
b1 `
b1 B
b10 %
b10 Y
1+
b10 ,
b10 X
b10 _
16
b1 3
b1 S
b1010 4
b1010 T
b1 8
b1 V
b10 Q
b1100000001010 7
b1100000001010 U
b1100000001010 [
b10 @
b10 Z
1!
#30
0!
#35
b1 <
b1 I
b1 J
b1 '
b1 L
b1 a
b100 -
b101000 K
b1 A
b1 `
b1 B
b10 (
b10 O
b10 ^
b1000 =
b1000 E
b1000 W
b0 %
b0 Y
1+
b11 ,
b11 X
b11 _
06
b101000 3
b101000 S
b101000011 4
b101000011 T
b1000 8
b1000 V
b11 Q
b1 *
b1 P
b1 ]
b11000 R
b1100000101000011 7
b1100000101000011 U
b1100000101000011 [
b11 @
b11 Z
1!
#40
0!
#45
b0 B
b0 '
b0 L
b0 a
b0 J
b101 -
b1000000 K
b0 (
b0 O
b0 ^
b1 )
b1 F
b1 b
1+
b1 ,
b1 X
b1 _
b0 =
b0 E
b0 W
b1000000 3
b1000000 S
b1000000001 4
b1000000001 T
b0 8
b0 V
b1 Q
b10 *
b10 P
b10 ]
b1101 R
b110101000000001 7
b110101000000001 U
b110101000000001 [
b100 @
b100 Z
1!
#50
0!
#55
b110 -
b1100000 K
1+
b10 ,
b10 X
b10 _
b1100000 3
b1100000 S
b1100000010 4
b1100000010 T
b10 Q
b11 *
b11 P
b11 ]
b110101100000010 7
b110101100000010 U
b110101100000010 [
b101 @
b101 Z
1!
#60
0!
#65
b1 B
b0 A
b0 `
b1 '
b1 L
b1 a
b0 <
b0 I
b11 (
b11 O
b11 ^
b111 -
b0 K
b0 )
b0 F
b0 b
1>
10
0+
b11 ,
b11 X
b11 _
b10100000 3
b10100000 S
b10100000011 4
b10100000011 T
b11 Q
b101 *
b101 P
b101 ]
b1111 R
b111110100000011 7
b111110100000011 U
b111110100000011 [
b110 @
b110 Z
1!
#70
0!
#75
b1 A
b1 `
b0 '
b0 L
b0 a
b1 <
b1 I
b1 J
b10100001 K
b1000 -
b0 (
b0 O
b0 ^
16
1+
b1100 =
b1100 E
b1100 W
b101 ,
b101 X
b101 _
0>
00
b10100001 3
b10100001 S
b10100001101 4
b10100001101 T
b1 8
b1 V
b101 Q
b11100 R
b1110010100001101 7
b1110010100001101 U
b1110010100001101 [
b111 @
b111 Z
1!
#80
0!
#85
b1 '
b1 L
b1 a
0&
0$
0/
1:
b11111111 G
b1001 -
b11001100 K
b0 A
b0 `
b1 B
b11 (
b11 O
b11 ^
0+
b0 ,
b0 X
b0 _
06
b1111 =
b1111 E
b1111 W
b0 <
b0 I
b101100011 J
b11001100 3
b11001100 S
b11001100000 4
b11001100000 T
b1100 8
b1100 V
b0 Q
b110 *
b110 P
b110 ]
b11111 R
b1100100 )
b1100100 F
b1100100 b
b1111111001100000 7
b1111111001100000 U
b1111111001100000 [
b1000 @
b1000 Z
1!
#90
0!
#95
b0 B
b0 '
b0 L
b0 a
1?
b0 J
b11 -
b11111111 K
b111 (
b111 O
b111 ^
b0 )
b0 F
b0 b
1;
b10 ,
b10 X
b10 _
b0 =
b0 E
b0 W
b11111111 3
b11111111 S
b11111111010 4
b11111111010 T
b11111 8
b11111 V
b10 Q
b111 *
b111 P
b111 ]
b1001 R
b100111111111010 7
b100111111111010 U
b100111111111010 [
b1001 @
b1001 Z
1!
#100
0!
#105
b1 B
b10 A
b10 `
b1 '
b1 L
b1 a
b10 <
b10 I
b10 J
b100 -
b101000 K
b10 (
b10 O
b10 ^
b1 )
b1 F
b1 b
1+
b1000 =
b1000 E
b1000 W
0;
b11 ,
b11 X
b11 _
b101000 3
b101000 S
b101000011 4
b101000011 T
b1000 8
b1000 V
b11 Q
b1 *
b1 P
b1 ]
b11000 R
0?
b1100000101000011 7
b1100000101000011 U
b1100000101000011 [
b11 @
b11 Z
1!
#110
0!
#115
b0 B
b1 A
b1 `
b0 '
b0 L
b0 a
b1 <
b1 I
b0 J
b101 -
b1000000 K
b0 (
b0 O
b0 ^
1+
b1 ,
b1 X
b1 _
b0 =
b0 E
b0 W
b1000000 3
b1000000 S
b1000000001 4
b1000000001 T
b0 8
b0 V
b1 Q
b10 *
b10 P
b10 ]
b1101 R
b110101000000001 7
b110101000000001 U
b110101000000001 [
b100 @
b100 Z
1!
#120
0!
#125
b10 A
b10 `
b10 <
b10 I
b110 -
b1100000 K
1+
b10 ,
b10 X
b10 _
b10 )
b10 F
b10 b
b1100000 3
b1100000 S
b1100000010 4
b1100000010 T
b10 Q
b11 *
b11 P
b11 ]
b110101100000010 7
b110101100000010 U
b110101100000010 [
b101 @
b101 Z
1!
#130
0!
#135
b10 B
b1 A
b1 `
b10 '
b10 L
b10 a
b1 <
b1 I
b11 (
b11 O
b11 ^
b111 -
b1 K
b1 )
b1 F
b1 b
1>
10
0+
b11 ,
b11 X
b11 _
b10100000 3
b10100000 S
b10100000011 4
b10100000011 T
b11 Q
b101 *
b101 P
b101 ]
b1111 R
b111110100000011 7
b111110100000011 U
b111110100000011 [
b110 @
b110 Z
1!
#140
0!
#145
b10 A
b10 `
b0 '
b0 L
b0 a
b1 B
b10 <
b10 I
b10 J
b10100001 K
b1000 -
b0 (
b0 O
b0 ^
16
1+
b1100 =
b1100 E
b1100 W
b101 ,
b101 X
b101 _
0>
00
b10100001 3
b10100001 S
b10100001101 4
b10100001101 T
b1 8
b1 V
b101 Q
b11100 R
b1110010100001101 7
b1110010100001101 U
b1110010100001101 [
b111 @
b111 Z
1!
#150
0!
#155
b10 '
b10 L
b10 a
1:
b11111110 G
b1001 -
b11001100 K
b10 B
b11 (
b11 O
b11 ^
0+
b0 ,
b0 X
b0 _
06
b1111 =
b1111 E
b1111 W
b0 A
b0 `
b11001100 3
b11001100 S
b11001100000 4
b11001100000 T
b1100 8
b1100 V
b0 Q
b110 *
b110 P
b110 ]
b11111 R
b0 <
b0 I
b101100010 J
b1111111001100000 7
b1111111001100000 U
b1111111001100000 [
b1100100 )
b1100100 F
b1100100 b
b1000 @
b1000 Z
1!
#160
0!
#165
b0 B
b0 '
b0 L
b0 a
1?
b0 J
b11 -
b11111111 K
b111 (
b111 O
b111 ^
b0 )
b0 F
b0 b
1;
b10 ,
b10 X
b10 _
b0 =
b0 E
b0 W
b11111111 3
b11111111 S
b11111111010 4
b11111111010 T
b11111 8
b11111 V
b10 Q
b111 *
b111 P
b111 ]
b1001 R
b100111111111010 7
b100111111111010 U
b100111111111010 [
b1001 @
b1001 Z
1!
#170
0!
#175
b10 B
b11 A
b11 `
b10 '
b10 L
b10 a
b11 <
b11 I
b11 J
b100 -
b101000 K
b10 (
b10 O
b10 ^
b1 )
b1 F
b1 b
1+
b1000 =
b1000 E
b1000 W
0;
b11 ,
b11 X
b11 _
b101000 3
b101000 S
b101000011 4
b101000011 T
b1000 8
b1000 V
b11 Q
b1 *
b1 P
b1 ]
b11000 R
0?
b1100000101000011 7
b1100000101000011 U
b1100000101000011 [
b11 @
b11 Z
1!
#180
0!
#185
b0 B
b10 A
b10 `
b0 '
b0 L
b0 a
b10 <
b10 I
b0 J
b101 -
b1000000 K
b0 (
b0 O
b0 ^
b10 )
b10 F
b10 b
1+
b1 ,
b1 X
b1 _
b0 =
b0 E
b0 W
b1000000 3
b1000000 S
b1000000001 4
b1000000001 T
b0 8
b0 V
b1 Q
b10 *
b10 P
b10 ]
b1101 R
b110101000000001 7
b110101000000001 U
b110101000000001 [
b100 @
b100 Z
1!
#190
0!
#195
b11 A
b11 `
b11 <
b11 I
b110 -
b1100000 K
1+
b10 ,
b10 X
b10 _
b11 )
b11 F
b11 b
b1100000 3
b1100000 S
b1100000010 4
b1100000010 T
b10 Q
b11 *
b11 P
b11 ]
b110101100000010 7
b110101100000010 U
b110101100000010 [
b101 @
b101 Z
1!
#200
0!
#205
b11 B
b10 A
b10 `
b11 '
b11 L
b11 a
b10 <
b10 I
b11 (
b11 O
b11 ^
b111 -
b10 K
b10 )
b10 F
b10 b
1>
10
0+
b11 ,
b11 X
b11 _
b10100000 3
b10100000 S
b10100000011 4
b10100000011 T
b11 Q
b101 *
b101 P
b101 ]
b1111 R
b111110100000011 7
b111110100000011 U
b111110100000011 [
b110 @
b110 Z
1!
#210
0!
#215
b11 A
b11 `
b0 '
b0 L
b0 a
b1 B
b11 <
b11 I
b11 J
b10100001 K
b1000 -
b0 (
b0 O
b0 ^
16
1+
b1100 =
b1100 E
b1100 W
b101 ,
b101 X
b101 _
0>
00
b10100001 3
b10100001 S
b10100001101 4
b10100001101 T
b1 8
b1 V
b101 Q
b11100 R
b1110010100001101 7
b1110010100001101 U
b1110010100001101 [
b111 @
b111 Z
1!
#220
0!
#225
b11 '
b11 L
b11 a
1:
b11111101 G
b1001 -
b11001100 K
b0 A
b0 `
b11 B
b11 (
b11 O
b11 ^
0+
b0 ,
b0 X
b0 _
06
b1111 =
b1111 E
b1111 W
b0 <
b0 I
b101100001 J
b11001100 3
b11001100 S
b11001100000 4
b11001100000 T
b1100 8
b1100 V
b0 Q
b110 *
b110 P
b110 ]
b11111 R
b1100100 )
b1100100 F
b1100100 b
b1111111001100000 7
b1111111001100000 U
b1111111001100000 [
b1000 @
b1000 Z
1!
#230
0!
#235
b0 B
b0 '
b0 L
b0 a
1?
b0 J
b11 -
b11111111 K
b111 (
b111 O
b111 ^
b0 )
b0 F
b0 b
1;
b10 ,
b10 X
b10 _
b0 =
b0 E
b0 W
b11111111 3
b11111111 S
b11111111010 4
b11111111010 T
b11111 8
b11111 V
b10 Q
b111 *
b111 P
b111 ]
b1001 R
b100111111111010 7
b100111111111010 U
b100111111111010 [
b1001 @
b1001 Z
1!
#240
0!
#245
b11 B
b101 A
b101 `
b11 '
b11 L
b11 a
b101 <
b101 I
b101 J
b100 -
b101000 K
b10 (
b10 O
b10 ^
b10 )
b10 F
b10 b
1+
b1000 =
b1000 E
b1000 W
0;
b11 ,
b11 X
b11 _
b101000 3
b101000 S
b101000011 4
b101000011 T
b1000 8
b1000 V
b11 Q
b1 *
b1 P
b1 ]
b11000 R
0?
b1100000101000011 7
b1100000101000011 U
b1100000101000011 [
b11 @
b11 Z
1!
#250
0!
#255
b0 B
b11 A
b11 `
b0 '
b0 L
b0 a
b11 <
b11 I
b0 J
b101 -
b1000000 K
b0 (
b0 O
b0 ^
b11 )
b11 F
b11 b
1+
b1 ,
b1 X
b1 _
b0 =
b0 E
b0 W
b1000000 3
b1000000 S
b1000000001 4
b1000000001 T
b0 8
b0 V
b1 Q
b10 *
b10 P
b10 ]
b1101 R
b110101000000001 7
b110101000000001 U
b110101000000001 [
b100 @
b100 Z
1!
#260
0!
#265
b101 A
b101 `
b101 <
b101 I
b110 -
b1100000 K
1+
b10 ,
b10 X
b10 _
b101 )
b101 F
b101 b
b1100000 3
b1100000 S
b1100000010 4
b1100000010 T
b10 Q
b11 *
b11 P
b11 ]
b110101100000010 7
b110101100000010 U
b110101100000010 [
b101 @
b101 Z
1!
#270
0!
#275
b101 B
b11 A
b11 `
b101 '
b101 L
b101 a
b11 <
b11 I
b11 (
b11 O
b11 ^
b111 -
b11 K
b11 )
b11 F
b11 b
1>
10
0+
b11 ,
b11 X
b11 _
b10100000 3
b10100000 S
b10100000011 4
b10100000011 T
b11 Q
b101 *
b101 P
b101 ]
b1111 R
b111110100000011 7
b111110100000011 U
b111110100000011 [
b110 @
b110 Z
1!
#280
0!
#285
b100 A
b100 `
b0 '
b0 L
b0 a
b1 B
b100 <
b100 I
b100 J
b10100001 K
b1000 -
b0 (
b0 O
b0 ^
16
1+
b1100 =
b1100 E
b1100 W
b101 ,
b101 X
b101 _
0>
00
b10100001 3
b10100001 S
b10100001101 4
b10100001101 T
b1 8
b1 V
b101 Q
b11100 R
b1110010100001101 7
b1110010100001101 U
b1110010100001101 [
b111 @
b111 Z
1!
#290
0!
#295
b101 '
b101 L
b101 a
1:
b11111011 G
b1001 -
b11001100 K
b101 B
b11 (
b11 O
b11 ^
0+
b0 ,
b0 X
b0 _
06
b1111 =
b1111 E
b1111 W
b0 A
b0 `
b11001100 3
b11001100 S
b11001100000 4
b11001100000 T
b1100 8
b1100 V
b0 Q
b110 *
b110 P
b110 ]
b11111 R
b0 <
b0 I
b101011111 J
b1111111001100000 7
b1111111001100000 U
b1111111001100000 [
b1100100 )
b1100100 F
b1100100 b
b1000 @
b1000 Z
1!
#300
0!
#305
b0 B
b0 '
b0 L
b0 a
1?
b0 J
b11 -
b11111111 K
b111 (
b111 O
b111 ^
b0 )
b0 F
b0 b
1;
b10 ,
b10 X
b10 _
b0 =
b0 E
b0 W
b11111111 3
b11111111 S
b11111111010 4
b11111111010 T
b11111 8
b11111 V
b10 Q
b111 *
b111 P
b111 ]
b1001 R
b100111111111010 7
b100111111111010 U
b100111111111010 [
b1001 @
b1001 Z
1!
#310
0!
