src/reg_file.v
//8 registers (R0-R7) of 16 bits each
//R0 is always 0
//R7 is reserved for JAL and RET but can be used
module reg_file(
    input wire clk,
    input wire rst,

    input wire we,
    input wire [2:0] wa,
    input wire [7:0] wd,

    input wire [2:0] ra1,
    output wire [7:0] rd1,

    input wire [2:0] ra2,
    output wire [7:0] rd2
);
    // 8 registers of 8 bits each
    reg [7:0] registers [0:7];

    // Write operation
    always @(posedge clk or posedge rst) begin
        if (rst) begin
            integer i;
            for (i = 0; i < 8; i = i + 1) begin
                registers[i] <= 8'b0;
            end
        end else if (we && (wa != 3'b0)) begin // Prevent writing to register 0 (which is always 0)
            registers[wa] <= wd;
        end
    end

    // Read operations
    assign rd1 = (ra1 == 3'd0) ? 8'h00 : registers[ra1];
    assign rd2 = (ra2 == 3'd0) ? 8'h00 : registers[ra2];
endmodule

testbenches/reg_file_testbench.v
`timescale 1ns / 1ps

module reg_file_testbench;

    // Inputs
    reg clk;
    reg rst;
    reg we;
    reg [2:0] wa;
    reg [15:0] wd;
    reg [2:0] ra1;
    reg [2:0] ra2;

    // Outputs
    wire [15:0] rd1;
    wire [15:0] rd2;

    // Instantiate the Unit Under Test (UUT)
    reg_file uut (
        .clk(clk), 
        .rst(rst), 
        .we(we), 
        .wa(wa), 
        .wd(wd), 
        .ra1(ra1), 
        .rd1(rd1), 
        .ra2(ra2), 
        .rd2(rd2)
    );

    // Clock generation (100MHz)
    always #5 clk = ~clk;

    initial begin
        $dumpfile("testbenches/reg_file_testbench.vcd");
        $dumpvars(0, reg_file_testbench);
        // Initialize Inputs
        clk = 0;
        rst = 1;
        we = 0;
        wa = 0;
        wd = 0;
        ra1 = 0;
        ra2 = 0;

        // 1. Reset Test
        #20 rst = 0;
        $display("--- Reset Complete ---");

        // 2. Write to R1 and R2
        #10;
        we = 1; wa = 3'd1; wd = 16'hAAAA; // Write 0xAAAA to R1
        #10;
        wa = 3'd2; wd = 16'h5555;        // Write 0x5555 to R2
        #10;
        we = 0;

        // 3. Read from R1 and R2 simultaneously
        ra1 = 3'd1;
        ra2 = 3'd2;
        #10;
        $display("R1 (expected AAAA): %h", rd1);
        $display("R2 (expected 5555): %h", rd2);

        // 4. Test R0 Invariant (Attempt to write to R0)
        we = 1; wa = 3'd0; wd = 16'hFFFF; 
        #10;
        we = 0; ra1 = 3'd0;
        #10;
        if (rd1 == 16'h0000) 
            $display("R0 Test Passed: R0 remains 0 despite write attempt.");
        else 
            $display("R0 Test Failed: R0 was overwritten with %h!", rd1);

        // 5. Test JAL/RET Register (R7)
        we = 1; wa = 3'd7; wd = 16'h1234;
        #10;
        we = 0; ra2 = 3'd7;
        #10;
        $display("R7 Test: %h", rd2);

        #50;
        $finish;
    end
      
endmodule

testbenches/reg_file_testbench.vcd
$date
	Thu Feb 19 12:55:13 2026
$end
$version
	Icarus Verilog
$end
$timescale
	1ps
$end
$scope module reg_file_testbench $end
$var wire 16 ! rd2 [15:0] $end
$var wire 16 " rd1 [15:0] $end
$var reg 1 # clk $end
$var reg 3 $ ra1 [2:0] $end
$var reg 3 % ra2 [2:0] $end
$var reg 1 & rst $end
$var reg 3 ' wa [2:0] $end
$var reg 16 ( wd [15:0] $end
$var reg 1 ) we $end
$scope module uut $end
$var wire 1 # clk $end
$var wire 3 * ra1 [2:0] $end
$var wire 3 + ra2 [2:0] $end
$var wire 1 & rst $end
$var wire 3 , wa [2:0] $end
$var wire 8 - wd [7:0] $end
$var wire 1 ) we $end
$var wire 8 . rd2 [7:0] $end
$var wire 8 / rd1 [7:0] $end
$scope begin $unm_blk_11 $end
$var integer 32 0 i [31:0] $end
$upscope $end
$upscope $end
$upscope $end
$enddefinitions $end
$comment Show the parameter values. $end
$dumpall
$end
#0
$dumpvars
b1000 0
b0 /
b0 .
b0 -
b0 ,
b0 +
b0 *
0)
b0 (
b0 '
1&
b0 %
b0 $
0#
b0 "
b0 !
$end
#5000
b1000 0
1#
#10000
0#
#15000
b1000 0
1#
#20000
0#
0&
#25000
1#
#30000
b10101010 -
0#
b1010101010101010 (
b1 '
b1 ,
1)
#35000
1#
#40000
b1010101 -
0#
b101010101010101 (
b10 '
b10 ,
#45000
1#
#50000
b1010101 !
b1010101 .
b10101010 "
b10101010 /
0#
b10 %
b10 +
b1 $
b1 *
0)
#55000
1#
#60000
b11111111 -
0#
b1111111111111111 (
b0 '
b0 ,
1)
#65000
1#
#70000
b0 "
b0 /
0#
b0 $
b0 *
0)
#75000
1#
#80000
b110100 -
0#
b1001000110100 (
b111 '
b111 ,
1)
#85000
1#
#90000
b110100 !
b110100 .
0#
b111 %
b111 +
0)
